Metadata-Version: 1.0
Name: ble-distributions
Version: 0.1
Summary: Binomial and Gaussian distributions
Home-page: UNKNOWN
Author: Blessing Okeke
Author-email: blessing.okekeou@gmail.com
License: UNKNOWN
Platform: UNKNOWN
